img2webp/__init__.py
img2webp/cli.py
img2webp/gui.py
img2webp-0.1.1.dist-info/LICENSE
img2webp-0.1.1.dist-info/METADATA
img2webp-0.1.1.dist-info/WHEEL
img2webp-0.1.1.dist-info/entry_points.txt
img2webp-0.1.1.dist-info/top_level.txt
img2webp-0.1.1.dist-info/RECORD
