Metadata-Version: 2.1
Name: img2webp
Version: 0.1.1
Summary: A tool to convert images to WebP format with both GUI and CLI interfaces
Author-email: "Bert Rico, ByteWise Analytics" <support@bytewise.app>
License: MIT License
Project-URL: homepage, https://github.com/bytewise-analytics/img2webp
Project-URL: issues, https://github.com/bytewise-analytics/img2webp/issues
Keywords: image,converter,webp,gui,cli
Classifier: Programming Language :: Python :: 3
Classifier: License :: OSI Approved :: MIT License
Classifier: Operating System :: OS Independent
Classifier: Environment :: Console
Requires-Python: >=3.7
License-File: LICENSE
Requires-Dist: Pillow>=9.0.0
Requires-Dist: setuptools>=45
